{
  "date": "2026-06-16",
  "generated_at": "2026-06-16T02:54:10.235368+08:00",
  "sections": [
    {
      "category": "主要",
      "sources": []
    },
    {
      "category": "更多",
      "sources": [
        {
          "name": "Solidot",
          "articles": [
            {
              "title": "瑞士选民否决了将人口设限千万的提案",
              "brief": "瑞士于6月14日举行全民公投，决定是否在2050年前将全国常住人口限制在1000万以内。由于人口增长主要依赖外来移民，右翼瑞士人民党提出该提案并主张放弃与欧盟的自由流动协议。最终54.79%的选民反对，45.21%支持，投票率58.86%，提案被否决。",
              "source_url": "https://www.solidot.org/story?sid=84589",
              "source_name": "Solidot",
              "published_at": "2026-06-15T23:51:26+08:00"
            },
            {
              "title": "俄罗斯计划退役漏气的国际空间站PrK模块",
              "brief": "国际空间站的PrK模块因结构裂缝持续漏气，今年初曾修复但近期漏气加剧，裂缝达16处。俄罗斯宇航员试图拆除承重支架遭NASA强烈反对，最终俄方通知NASA将退役该模块。此后宇航员不再进入PrK模块，俄罗斯需改用其他端口补给。",
              "source_url": "https://www.solidot.org/story?sid=84588",
              "source_name": "Solidot",
              "published_at": "2026-06-15T23:35:55+08:00"
            },
            {
              "title": "Arch Linux遭遇新一轮AUR恶意程序攻击",
              "brief": "Arch Linux的用户软件仓库AUR上周遭大规模恶意攻击，处理逾1500个软件包后开发者认为已控制，但仅过一天又遭新一轮攻击，攻击者使用代码混淆技术。AUR并非官方库，项目可能需暂时下线以应对持续攻击。",
              "source_url": "https://www.solidot.org/story?sid=84587",
              "source_name": "Solidot",
              "published_at": "2026-06-15T23:04:50+08:00"
            }
          ]
        },
        {
          "name": "IT之家",
          "articles": [
            {
              "title": "苹果 watchOS 26.6 开发者预览版 Beta 2 发布",
              "brief": "苹果推送了 watchOS 26.6 开发者预览版 Beta 2 更新，版本号为 23U5025e。该版本主要面向注册苹果开发者计划的用户，可通过设置中的软件更新进行升级。目前具体更新内容尚未公布，预计将修复已知问题并提升性能。",
              "source_url": "https://www.ithome.com/0/964/609.htm",
              "source_name": "IT之家",
              "published_at": "2026-06-16T01:16:10+08:00"
            },
            {
              "title": "苹果 visionOS 26.6 开发者预览版 Beta 2 发布",
              "brief": "苹果推送了 visionOS 26.6 开发者预览版 Beta 2 更新，版本号为 23O5728e。该版本面向注册苹果开发者计划的用户，可通过系统设置中的软件更新升级。目前具体更新内容尚未公布，预计将改进系统稳定性和用户体验。",
              "source_url": "https://www.ithome.com/0/964/608.htm",
              "source_name": "IT之家",
              "published_at": "2026-06-16T01:16:10+08:00"
            },
            {
              "title": "苹果 macOS 26.6 开发者预览版 Beta 2 发布",
              "brief": "苹果推送了 macOS 26.6 开发者预览版 Beta 2 更新，版本号为 25G5028f。该版本面向注册苹果开发者计划的用户，可通过系统设置中的软件更新升级。目前具体更新内容尚未公布，预计将修复漏洞并提升系统性能。",
              "source_url": "https://www.ithome.com/0/964/607.htm",
              "source_name": "IT之家",
              "published_at": "2026-06-16T01:16:09+08:00"
            },
            {
              "title": "苹果 iOS/iPadOS 26.6 开发者预览版 Beta 2 发布",
              "brief": "苹果推送了 iOS/iPadOS 26.6 开发者预览版 Beta 2 更新，版本号为 23G5028e。该版本面向注册苹果开发者计划的用户，可通过系统设置中的软件更新升级。目前具体更新内容尚未公布，预计将修复错误并优化系统流畅度。",
              "source_url": "https://www.ithome.com/0/964/606.htm",
              "source_name": "IT之家",
              "published_at": "2026-06-16T01:16:09+08:00"
            },
            {
              "title": "华为鸿蒙HarmonyOS 7开发者Beta版推送，系统扩展特性同步更新",
              "brief": "华为开始推送鸿蒙HarmonyOS 7 Developer Beta 1版，同步更新系统扩展特性以提升用户体验。该版本于6月12日发布，并开启公开招募。首批支持机型包括Mate 80 Pro、Mate X7、Mate XTs非凡大师、Pura 90 Pro Max、Pura X、Pura X典藏版和nova 15 Pro。此外，HarmonyOS开发套件26.0.0 Beta1也在HDC 2026面向开发者发布。",
              "source_url": "https://www.ithome.com/0/964/605.htm",
              "source_name": "IT之家",
              "published_at": "2026-06-15T23:59:16+08:00"
            }
          ]
        }
      ]
    }
  ]
}